{"completed": true, "subtasks": {"subtask_0": {"obj_name": "pointRobot-vel-v7", "target_state_pos_2d": [-1.3212, 1.0, 0.0], "completed": true, "num_hypotheses": 1, "hypotheses": {"hypothesis_1": {"edges": {"edge_0": {"status": "edge:completed", "verb": "driving", "controller_type": "MPC", "final_pose_error": null, "avg_pred_error": 0.0, "max_pred_error": 0.0, "min_pred_error": 0.0}}, "num_edges": 1, "completed": true, "search_time": 0.02818608283996582, "execute_time": 1.7952258586883545, "total_time": 1.8234119415283203}}, "search_time": 0.02818608283996582, "execute_time": 1.7952258586883545, "total_time": 1.8234119415283203}, "subtask_1": {"obj_name": "pointRobot-vel-v7", "target_state_pos_2d": [3.3212, 2.2, 0.0], "completed": true, "num_hypotheses": 1, "hypotheses": {"hypothesis_1": {"edges": {"edge_0": {"status": "edge:completed", "verb": "identify"}, "edge_1": {"status": "edge:completed", "verb": "driving", "controller_type": "MPC", "final_pose_error": null, "avg_pred_error": 0.0, "max_pred_error": 0.0, "min_pred_error": 0.0}}, "num_edges": 2, "completed": true, "search_time": 1.404057264328003, "execute_time": 2.9929089546203613, "total_time": 4.396966218948364}}, "search_time": 1.404057264328003, "execute_time": 2.9929089546203613, "total_time": 4.396966218948364}, "subtask_2": {"obj_name": "pointRobot-vel-v7", "target_state_pos_2d": [-4, -4, 0], "completed": true, "num_hypotheses": 1, "hypotheses": {"hypothesis_1": {"edges": {"edge_0": {"status": "edge:completed", "verb": "identify"}, "edge_1": {"status": "edge:completed", "verb": "driving", "controller_type": "MPPI", "final_pose_error": null, "avg_pred_error": 9e-05, "max_pred_error": 0.00412, "min_pred_error": 0.0}}, "num_edges": 2, "completed": true, "search_time": 0.8600125312805176, "execute_time": 3.363743305206299, "total_time": 4.223755836486816}}, "search_time": 0.8600125312805176, "execute_time": 3.363743305206299, "total_time": 4.223755836486816}}, "total_time": 10.444133996963501, "execute_time": 8.151878118515015, "search_time": 2.2922558784484863, "hypothesis_success_ratio": 1.0}